reading/__init__.py
reading/_core.py
reading/books/README.md
reading/books/软件下载导航.md
reading/books/codes/README.md
reading/books/codes/chromium/教程.md
reading/books/codes/docker/docker.md
reading/books/codes/docker/创建常用容器.md
reading/books/codes/docker/容器.md
reading/books/codes/java/安装.md
reading/books/codes/java/demo/Main.java
reading/books/codes/java/springboot/安装.md
reading/books/codes/linux/ssh.md
reading/books/codes/linux/常用指令.md
reading/books/codes/python/README.md
reading/books/codes/python/uiautomator2/README.md
reading/books/codes/python/uiautomator2/语法.md
reading/books/codes/python/uiautomator2/安装/index.md
reading/books/codes/python/uiautomator2/安装/start_wechat.py
reading/books/codes/python/安装/1.png
reading/books/codes/python/安装/index.md
reading/books/codes/react/README.md
reading/books/codes/react/响应事件.md
reading/books/codes/react/组件.md
reading/books/manuscript/README.md
reading/books/manuscript/docs/唯一观察器意识模型.md
reading/books/ninjacode/README.md
reading/books/ninjacode/ninjutsu/别天神.md
reading/books/ninjacode/ninjutsu/咒印.md
reading/books/ninjacode/ninjutsu/封印.md
reading/books/ninjacode/ninjutsu/尸鬼封尽.md
reading/books/ninjacode/ninjutsu/影分身.md
reading/books/ninjacode/ninjutsu/秽土转生.md
reading/books/ninjacode/ninjutsu/血继限界.md
reading/books/ninjacode/ninjutsu/须佐能乎.md
reading/books/ninjacode/ninjutsu/飞雷神.md
reading-2025.4.3.dist-info/WHEEL
reading-2025.4.3.dist-info/METADATA
reading-2025.4.3.dist-info/RECORD
