Metadata-Version: 2.4
Name: reading
Version: 2025.4.3
Summary: 一个文本离线朗读软件。用户既可以在界面上输入文本进行朗读，也能选择本地的文本文件进行全文朗读
Author-email: 许灿标 <lcctoor@outlook.com>
Requires-Python: >=3.12
Requires-Dist: tornado
